deepracer_vehicle_api/__init__.py
deepracer_vehicle_api/client.py
tests/__init__.py
tests/test_1.py
deepracer_vehicle_api-0.0.10.dist-info/LICENSE
deepracer_vehicle_api-0.0.10.dist-info/METADATA
deepracer_vehicle_api-0.0.10.dist-info/WHEEL
deepracer_vehicle_api-0.0.10.dist-info/top_level.txt
deepracer_vehicle_api-0.0.10.dist-info/RECORD
