Metadata-Version: 2.1
Name: deepracer-vehicle-api
Version: 0.0.10
Summary: deepracer-vehicle-api is a python package for control the DeepRacer vehicle via HTTP API.
Home-page: https://github.com/thu2004/deepracer-vehicle-api
Author: Chi Thu Le
Author-email: thu2004@yahoo.se
License: MIT
Platform: UNKNOWN
Classifier: Development Status :: 3 - Alpha
Classifier: License :: OSI Approved :: MIT License
Classifier: Programming Language :: Python :: 3.7
Classifier: Topic :: Software Development :: Libraries
Classifier: Topic :: Software Development :: Libraries :: Python Modules
Classifier: Intended Audience :: Developers
Requires-Python: >=3.6
Requires-Dist: beautifulsoup4 (>=4.8.2)
Requires-Dist: bs4 (>=0.0.1)
Requires-Dist: lxml (>=4.4.2)
Requires-Dist: PyYAML (>=5.3)
Requires-Dist: requests (>=2.22.0)
Requires-Dist: requests-toolbelt (>=0.9.1)
Requires-Dist: urllib3 (>=1.25.8)
